[
  {
    "name": "Wolfram Research",
    "shortName": "Wolfram",
    "title": "Software Engineer",
    "startDate": "Aug 2020",
    "endDate": "Present",
    "techStack": "React, Java, Wolfram Language",
    "responsibilities": [
      "Developing and maintaining http://wolframcloud.com using the React, Java Spring Boot and Wolfram Language technologies.",
      "Responsible for the FormFunction repository, which represents an active form with Wolfram Language.",
      "Worked on some side projects with React, Webpack, Java, and Wolfram Language."
    ]
  },
  {
    "name": "Destek Engineering",
    "shortName": "Destek",
    "title": "Full Stack Web Developer",
    "startDate": "Feb 2018",
    "endDate": "Aug 2020",
    "techStack": "JavaScript ES6, React, Vue, Node, AWS, Docker, Linux, Redis, Postgresql, Cypress, Postman, Jira",
    "responsibilities": [
      "Worked on the architectural design of the system.",
      "Responsible for people management, including goal setting and providing performance feedback.",
      "Implement front-end features using React and MaterialUI and Vue and ElementUI.",
      "Write E2E tests with Cypress and API tests with Postman.",
      "Implement Authentication System using JWT and Redis.",
      "Delivered an educational web application using React and Node, and an e-commerce portal using Laravel and Vue.",
      "CI/CD experience with Docker and AWS."
    ]
  },
  {
    "name": " Bulutsoft Software",
    "shortName": "Bulutsoft",
    "title": "Frontend Heavy Full Stack Web Developer",
    "startDate": "Jan 2016",
    "endDate": "Dec 2017",
    "techStack": "HTML, CSS, PHP, Laravel, Jquery, Mysql, REST & SOAP, Git",
    "responsibilities": [
      "Experience with HTML, CSS, software development life cycle.",
      "Developed a CRM (for Tourism Agencies) with PHP(Laravel) and Jquery."
    ]
  }
]
